allya/nestedconfigparser/__init__.py
allya.nestedconfigparser-0.1.0.dist-info/DESCRIPTION.rst
allya.nestedconfigparser-0.1.0.dist-info/METADATA
allya.nestedconfigparser-0.1.0.dist-info/RECORD
allya.nestedconfigparser-0.1.0.dist-info/WHEEL
allya.nestedconfigparser-0.1.0.dist-info/metadata.json
allya.nestedconfigparser-0.1.0.dist-info/top_level.txt
allya.nestedconfigparser-0.1.0.dist-info/zip-safe
