Metadata-Version: 2.0
Name: allya.nestedconfigparser
Version: 0.1.0
Summary: A simple extension to configparser that allows nested fallback configurations
Home-page: https://github.com/Kazzer/nestedconfigparser
Author: Kadeem Hassam
Author-email: kadeem.hassam@peckypanda.com
License: WTFPL
Keywords: configparser Nested Recursive
Platform: UNKNOWN
Classifier: Development Status :: 4 - Beta
Classifier: Intended Audience :: Developers
Classifier: License :: Other/Proprietary License
Classifier: Natural Language :: English
Classifier: Operating System :: OS Independent
Classifier: Programming Language :: Python :: 3
Classifier: Programming Language :: Python :: 3.3
Classifier: Programming Language :: Python :: 3.4
Classifier: Programming Language :: Python :: 3 :: Only
Classifier: Topic :: Utilities
